{
  "lemma": "anxiety",
  "slug": "anxiety",
  "fetchTerm": "anxiety",
  "en": [
    {
      "partOfSpeech": "Noun",
      "definitions": [
        {
          "text": "An unpleasant state of mental uneasiness, nervousness, apprehension and obsession or concern about some uncertain event.",
          "examples": [
            "generalized anxiety disorder",
            "feel anxiety"
          ]
        },
        {
          "text": "An uneasy or distressing desire (for something). Endeavor (to please).",
          "examples": []
        },
        {
          "text": "A state of restlessness and agitation, often accompanied by a distressing sense of oppression or tightness in the stomach.",
          "examples": []
        }
      ]
    }
  ],
  "pl": null,
  "translations": [
    "niepokój",
    "trwoga",
    "lęk"
  ],
  "fetchedAt": "2026-05-17T22:33:42.461Z"
}
